vst/audio_to_wav.py
vst/classes/languages.py
vst/classes/process.py
vst/classes/shell.py
vst/classes/wavfile.py
vst/en_to_pl.py
vst/translation/en_to_pl.py
vst/wav_splitter.py
vst/wav_to_text.py
vst-22.7.13.dist-info/entry_points.txt
vst-22.7.13.dist-info/WHEEL
vst-22.7.13.dist-info/METADATA
vst-22.7.13.dist-info/RECORD
